Metadata-Version: 1.1
Name: clean-excel
Version: 1.0.1
Summary: Parse and filter any chaotic excel sheet into a formatted numpy array or pandas dataframe.
Home-page: UNKNOWN
Author: Timo Kats
Author-email: tpakats@gmail.com
License: MIT
Keywords: excel
Platform: UNKNOWN
Classifier: Development Status :: 4 - Beta
Classifier: Environment :: Console
Classifier: Intended Audience :: Developers
Classifier: License :: OSI Approved :: MIT License
Classifier: Operating System :: Microsoft :: Windows
Classifier: Programming Language :: Python :: 3
